MANIFEST.in
README.rst
setup.py
streettraffic/__init__.py
streettraffic/database.py
streettraffic/datafeed.py
streettraffic/log.py
streettraffic/server.py
streettraffic/tools.py
streettraffic.egg-info/PKG-INFO
streettraffic.egg-info/SOURCES.txt
streettraffic.egg-info/dependency_links.txt
streettraffic.egg-info/requires.txt
streettraffic.egg-info/top_level.txt
streettraffic/map_resource/__init__.py
streettraffic/map_resource/utility.py
streettraffic/predefined/__init__.py
streettraffic/predefined/cities.py
streettraffic/tests/__init__.py
streettraffic/tests/test_database.py
streettraffic/tests/test_utility.py
streettraffic/webui/index.html
streettraffic/webui/static/css/app.f219a4b517a2b442188171e3c971eaea.css
streettraffic/webui/static/css/app.f219a4b517a2b442188171e3c971eaea.css.map
streettraffic/webui/static/js/0.5bdaa9a5313598954716.js
streettraffic/webui/static/js/0.5bdaa9a5313598954716.js.map
streettraffic/webui/static/js/1.1c680c81b4bd58d30eb6.js
streettraffic/webui/static/js/1.1c680c81b4bd58d30eb6.js.map
streettraffic/webui/static/js/10.793d9c5ef82afd9e9c8e.js
streettraffic/webui/static/js/10.793d9c5ef82afd9e9c8e.js.map
streettraffic/webui/static/js/11.6c1ad8c2e4be296c5fbd.js
streettraffic/webui/static/js/11.6c1ad8c2e4be296c5fbd.js.map
streettraffic/webui/static/js/12.e2205c5f70c1e360974b.js
streettraffic/webui/static/js/12.e2205c5f70c1e360974b.js.map
streettraffic/webui/static/js/13.9924391e97aef699e471.js
streettraffic/webui/static/js/13.9924391e97aef699e471.js.map
streettraffic/webui/static/js/14.d14c9c1987cc94988014.js
streettraffic/webui/static/js/14.d14c9c1987cc94988014.js.map
streettraffic/webui/static/js/15.3566a45bf8d06d4fe26e.js
streettraffic/webui/static/js/15.3566a45bf8d06d4fe26e.js.map
streettraffic/webui/static/js/2.eb9696bd15d7de63f245.js
streettraffic/webui/static/js/2.eb9696bd15d7de63f245.js.map
streettraffic/webui/static/js/3.1a167ffb5272e3977b64.js
streettraffic/webui/static/js/3.1a167ffb5272e3977b64.js.map
streettraffic/webui/static/js/4.af5ad151ea0c5a47b35a.js
streettraffic/webui/static/js/4.af5ad151ea0c5a47b35a.js.map
streettraffic/webui/static/js/5.213b7fc08b4238238183.js
